Workbook

Sheet BS of DBP
A1: Balance Sheet of Deshbandhu Polymer Limited
A3: Particulars | C3: 2022 | D3: 2021 | E3: 2020 | F3: 2019 | G3: 2018
A4: Property, plant and equipment | C4: 1015509672 | D4: 1031206714 | E4: 459619411 | F4: 441596074 | G4: 514937045
A5: Investments | C5: 824901 | D5: 877876 | E5: 716928 | F5: 716928 | G5: 716928
A6: Accumulated Depreciation | C6: - | D6: - | E6: - | F6: - | G6: -160511475
A7: Total Non-current assets | C7: 1016334574 | D7: 1032084591 | E7: 460336339 | F7: 442313002 | G7: 355142498
A8: Inventories | C8: 401412927 | D8: 284952963 | E8: 282126699 | F8: 220491223 | G8: 143522703
A9: AccOUnt Receivables | C9: 298283337 | D9: 289744796 | E9: 262457625 | F9: 267304556 | G9: 300323635
A10: Inventories in transit | C10: 188710823 | D10: 188293077 | E10: 305851655 | F10: 446329786 | G10: 373854439
A11: Inter comnany receivable | C11: - | D11: 171378178 | E11: 219552032 | F11: 158594340 | G11: 178987434
A12: Advances, deposits and prepayments | C12: 215347109 | D12: 224070875 | E12: 165312520 | F12: 141797403 | G12: 169892545
A13: Advance Income tax | C13: 361213480 | D13: 326047287 | E13: 291132330 | F13: 255144068 | G13: 223311071
A14: Cash and cash equivalents | C14: 13964956 | D14: 26962658 | E14: 18629400 | F14: 28249941 | G14: 15844062
A15: Total Currant assets | C15: 1478932632 | D15: 1511449834 | E15: 1545062262 | F15: 1517911318 | G15: 1405735889
A16: Total assets | C16: 2495267206 | D16: 2543534425 | E16: 2005398601 | F16: 1960224320 | G16: 1760878387
A17: Stated canital | C17: 613651500 | D17: 613651500 | E17: 613651500 | F17: 613651500 | G17: 613651500
A18: Revaluation Reserve | C18: 467003358 | D18: 473502357 | E18: - | F18: - | G18: -
A19: Retained Earnings | C19: 36712385 | D19: 21469808 | E19: 29737202 | F19: 43906010 | G19: 45845539
A20: Equity attributable to owners or the company | C20: 1117367243 | D20: 1108623665 | E20: 643388702 | F20: 657557510 | G20: 659497039
A21: Total equity | C21: 1117367243 | D21: 1108623665 | E21: 643388702 | F21: 657557510 | G21: 659497039
A22: Long Term Borrowings/Loan | C22: 375172771 | D22: 410859778 | E22: - | F22: - | G22: -
A23: Defferred Tax Liabilities | C23: 157771520 | D23: 166337103 | E23: 66992628 | F23: 66489985 | G23: 70797650
A24: Total Non-current liabilities | C24: 532944291 | D24: 577196881 | E24: 66992628 | F24: 66489985 | G24: 70797650
A25: Short-term borrowings - secured | C25: 552345251 | D25: 536354828 | E25: 994809360 | F25: 917161001 | G25: 717600546
A26: Other Pavable | C26: 50423520 | D26: 68574255 | E26: 9201738 | F26: 14356838 | G26: 8039454
A27: Bank overdraft | C27: 214972098 | D27: 235091322 | E27: 217466613 | F27: 234645434 | G27: 240658591
A28: Workers' Profit Participation Fund | C28: 1342061 | D28: 476309 | E28: 2219381 | F28: 1629025 | G28: 2188695
A29: Accounts and other payable | C29: 1739657 | D29: 2292664 | E29: 3584202 | F29: 5730154 | G29: 7587964
A30: share money refundable | C30: 14924500 | D30: 14924500 | E30: 14924500 | F30: 14924500 | G30: 14924500
A31: Provision for Tax I abilities/ Current Tax I ability | C31: - | D31: - | E31: 52811477 | F31: 47729073 | G31: 39583946
A32: Unclaimed Dividend | C32: 9208586 | D32: - | E32: - | F32: - | G32: -
A33: Total Current liabilities | C33: 844955673 | D33: 857713878 | E33: 1295017974 | F33: 1236176825 | G33: 1030583696
A34: Total equity and liabilities | C34: 495267208 | D34: 3543534495 | E34: 2005398601 | F34: 1960224320 | G34: 1760878385
A35: Market Price | C35: 18.1 | D35: 20.6 | E35: 11.55 | F35: 11.13 | G35: 14.38

Sheet Vertical Analysis(BS) of DBP
A1: Balance Sheet of Deshbandhu Polymer Limited (Vertical Analysis)
A3: Particulars | B3: 2022 | C3: Vertical Analysis | D3: 2021 | E3: Vertical Analysis | F3: 2020 | G3: Vertical Analysis | H3: 2019 | I3: Vertical Analysis | J3: 2018 | K3: Vertical Analysis
A4: Property, plant and equipment | B4: 1015509672 | C4: =B4/$B$16 -> 0.40697432 | D4: 1031206714 | E4: =D4/$D$16 -> 0.40542275 | F4: 459619411 | G4: =F4/$F$16 -> 0.22919105 | H4: 441596074 | I4: =H4/$H$16 -> 0.22527834 | J4: 514937045 | K4: =J4/$J$16 -> 0.29243192
A5: Investments | B5: 824901 | C5: =B5/$B$16 -> 0.00033058624 | D5: 877876 | E5: =D5/$D$16 -> 0.00034514021 | F5: 716928 | G5: =F5/$F$16 -> 0.000357499 | H5: 716928 | I5: =H5/$H$16 -> 0.00036573773 | J5: 716928 | K5: =J5/$J$16 -> 0.00040714226
A6: Accumulated Depreciation | B6: - | C6: - | D6: - | E6: - | F6: - | G6: - | H6: - | I6: - | J6: -160511475 | K6: =J6/$J$16 -> -0.091154208
A7: Total Non-current assets | B7: 1016334574 | C7: =B7/$B$16 -> 0.40730491 | D7: 1032084591 | E7: =D7/$D$16 -> 0.40576789 | F7: 460336339 | G7: =F7/$F$16 -> 0.22954855 | H7: 442313002 | I7: =H7/$H$16 -> 0.22564407 | J7: 355142498 | K7: =J7/$J$16 -> 0.20168485
A8: Inventories | B8: 401412927 | C8: =B8/$B$16 -> 0.16086972 | D8: 284952963 | E8: =D8/$D$16 -> 0.11203032 | F8: 282126699 | G8: =F8/$F$16 -> 0.1406836 | H8: 220491223 | I8: =H8/$H$16 -> 0.11248265 | J8: 143522703 | K8: =J8/$J$16 -> 0.081506312
A9: AccOUnt Receivables | B9: 298283337 | C9: =B9/$B$16 -> 0.11953964 | D9: 289744796 | E9: =D9/$D$16 -> 0.11391424 | F9: 262457625 | G9: =F9/$F$16 -> 0.13087554 | H9: 267304556 | I9: =H9/$H$16 -> 0.13636427 | J9: 300323635 | K9: =J9/$J$16 -> 0.17055331
A10: Inventories in transit | B10: 188710823 | C10: =B10/$B$16 -> 0.075627501 | D10: 188293077 | E10: =D10/$D$16 -> 0.074028122 | F10: 305851655 | G10: =F10/$F$16 -> 0.15251415 | H10: 446329786 | I10: =H10/$H$16 -> 0.22769322 | J10: 373854439 | K10: =J10/$J$16 -> 0.21231133
A11: Inter comnany receivable | B11: - | C11: - | D11: 171378178 | E11: =D11/$D$16 -> 0.067377967 | F11: 219552032 | G11: =F11/$F$16 -> 0.1094805 | H11: 158594340 | I11: =H11/$H$16 -> 0.08090622 | J11: 178987434 | K11: =J11/$J$16 -> 0.10164668
A12: Advances, deposits and prepayments | B12: 215347109 | C12: =B12/$B$16 -> 0.086302224 | D12: 224070875 | E12: =D12/$D$16 -> 0.088094296 | F12: 165312520 | G12: =F12/$F$16 -> 0.082433747 | H12: 141797403 | I12: =H12/$H$16 -> 0.072337335 | J12: 169892545 | K12: =J12/$J$16 -> 0.096481703
A13: Advance Income tax | B13: 361213480 | C13: =B13/$B$16 -> 0.14475944 | D13: 326047287 | E13: =D13/$D$16 -> 0.1281867 | F13: 291132330 | G13: =F13/$F$16 -> 0.1451743 | H13: 255144068 | I13: =H13/$H$16 -> 0.13016065 | J13: 223311071 | K13: =J13/$J$16 -> 0.126818
A14: Cash and cash equivalents | B14: 13964956 | C14: =B14/$B$16 -> 0.0055965774 | D14: 26962658 | E14: =D14/$D$16 -> 0.010600469 | F14: 18629400 | G14: =F14/$F$16 -> 0.0092896245 | H14: 28249941 | I14: =H14/$H$16 -> 0.014411586 | J14: 15844062 | K14: =J14/$J$16 -> 0.0089978173
A15: Total Currant assets | B15: 1478932632 | C15: =B15/$B$16 -> 0.59269509 | D15: 1511449834 | E15: =D15/$D$16 -> 0.59423211 | F15: 1545062262 | G15: =F15/$F$16 -> 0.77045145 | H15: 1517911318 | I15: =H15/$H$16 -> 0.77435593 | J15: 1405735889 | K15: =J15/$J$16 -> 0.79831515
A16: Total assets | B16: 2495267206 | C16: =B16/$B$16 -> 1 | D16: 2543534425 | E16: =D16/$D$16 -> 1 | F16: 2005398601 | G16: =F16/$F$16 -> 1 | H16: 1960224320 | I16: =H16/$H$16 -> 1 | J16: 1760878387 | K16: =J16/$J$16 -> 1
A17: Stated canital | B17: 613651500 | C17: =B17/$B$16 -> 0.24592617 | D17: 613651500 | E17: =D17/$D$16 -> 0.24125936 | F17: 613651500 | G17: =F17/$F$16 -> 0.30599976 | H17: 613651500 | I17: =H17/$H$16 -> 0.31305167 | J17: 613651500 | K17: =J17/$J$16 -> 0.3484917
A18: Revaluation Reserve | B18: 467003358 | C18: =B18/$B$16 -> 0.18715565 | D18: 473502357 | E18: =D18/$D$16 -> 0.18615921 | F18: - | G18: - | H18: - | I18: - | J18: - | K18: -
A19: Retained Earnings | B19: 36712385 | C19: =B19/$B$16 -> 0.014712807 | D19: 21469808 | E19: =D19/$D$16 -> 0.0084409347 | F19: 29737202 | G19: =F19/$F$16 -> 0.014828574 | H19: 43906010 | I19: =H19/$H$16 -> 0.022398462 | J19: 45845539 | K19: =J19/$J$16 -> 0.026035608
A20: Equity attributable to owners or the company | B20: 1117367243 | C20: =B20/$B$16 -> 0.44779463 | D20: 1108623665 | E20: =D20/$D$16 -> 0.43585951 | F20: 643388702 | G20: =F20/$F$16 -> 0.32082834 | H20: 657557510 | I20: =H20/$H$16 -> 0.33545013 | J20: 659497039 | K20: =J20/$J$16 -> 0.37452731
A21: Total equity | B21: 1117367243 | C21: =B21/$B$16 -> 0.44779463 | D21: 1108623665 | E21: =D21/$D$16 -> 0.43585951 | F21: 643388702 | G21: =F21/$F$16 -> 0.32082834 | H21: 657557510 | I21: =H21/$H$16 -> 0.33545013 | J21: 659497039 | K21: =J21/$J$16 -> 0.37452731
A22: Long Term Borrowings/Loan | B22: 375172771 | C22: =B22/$B$16 -> 0.15035375 | D22: 410859778 | E22: =D22/$D$16 -> 0.16153105 | F22: - | G22: - | H22: - | I22: - | J22: - | K22: -
A23: Defferred Tax Liabilities | B23: 157771520 | C23: =B23/$B$16 -> 0.063228307 | D23: 166337103 | E23: =D23/$D$16 -> 0.065396049 | F23: 66992628 | G23: =F23/$F$16 -> 0.033406141 | H23: 66489985 | I23: =H23/$H$16 -> 0.03391958 | J23: 70797650 | K23: =J23/$J$16 -> 0.040205871
A24: Total Non-current liabilities | B24: 532944291 | C24: =B24/$B$16 -> 0.21358205 | D24: 577196881 | E24: =D24/$D$16 -> 0.2269271 | F24: 66992628 | G24: =F24/$F$16 -> 0.033406141 | H24: 66489985 | I24: =H24/$H$16 -> 0.03391958 | J24: 70797650 | K24: =J24/$J$16 -> 0.040205871
A25: Short-term borrowings - secured | B25: 552345251 | C25: =B25/$B$16 -> 0.22135716 | D25: 536354828 | E25: =D25/$D$16 -> 0.21086989 | F25: 994809360 | G25: =F25/$F$16 -> 0.49606565 | H25: 917161001 | I25: =H25/$H$16 -> 0.46788574 | J25: 717600546 | K25: =J25/$J$16 -> 0.40752419
A26: Other Pavable | B26: 50423520 | C26: =B26/$B$16 -> 0.020207663 | D26: 68574255 | E26: =D26/$D$16 -> 0.026960223 | F26: 9201738 | G26: =F26/$F$16 -> 0.0045884833 | H26: 14356838 | I26: =H26/$H$16 -> 0.0073240791 | J26: 8039454 | K26: =J26/$J$16 -> 0.004565593
A27: Bank overdraft | B27: 214972098 | C27: =B27/$B$16 -> 0.086151935 | D27: 235091322 | E27: =D27/$D$16 -> 0.092427026 | F27: 217466613 | G27: =F27/$F$16 -> 0.10844059 | H27: 234645434 | I27: =H27/$H$16 -> 0.11970336 | J27: 240658591 | K27: =J27/$J$16 -> 0.13666963
A28: Workers' Profit Participation Fund | B28: 1342061 | C28: =B28/$B$16 -> 0.0005378426 | D28: 476309 | E28: =D28/$D$16 -> 0.00018726265 | F28: 2219381 | G28: =F28/$F$16 -> 0.0011067032 | H28: 1629025 | I28: =H28/$H$16 -> 0.00083104009 | J28: 2188695 | K28: =J28/$J$16 -> 0.0012429564
A29: Accounts and other payable | B29: 1739657 | C29: =B29/$B$16 -> 0.00069718265 | D29: 2292664 | E29: =D29/$D$16 -> 0.00090136936 | F29: 3584202 | G29: =F29/$F$16 -> 0.0017872766 | H29: 5730154 | I29: =H29/$H$16 -> 0.0029232134 | J29: 7587964 | K29: =J29/$J$16 -> 0.0043091925
A30: share money refundable | B30: 14924500 | C30: =B30/$B$16 -> 0.005981123 | D30: 14924500 | E30: =D30/$D$16 -> 0.0058676226 | F30: 14924500 | G30: =F30/$F$16 -> 0.0074421614 | H30: 14924500 | I30: =H30/$H$16 -> 0.0076136694 | J30: 14924500 | K30: =J30/$J$16 -> 0.0084755995
A31: Provision for Tax I abilities/ Current Tax I ability | B31: - | C31: - | D31: - | E31: - | F31: 52811477 | G31: =F31/$F$16 -> 0.026334653 | H31: 47729073 | I31: =H31/$H$16 -> 0.024348781 | J31: 39583946 | K31: =J31/$J$16 -> 0.022479659
A32: Unclaimed Dividend | B32: 9208586 | C32: =B32/$B$16 -> 0.0036904208 | D32: - | E32: - | F32: - | G32: - | H32: - | I32: - | J32: - | K32: -
A33: Total Current liabilities | B33: 844955673 | C33: =B33/$B$16 -> 0.33862332 | D33: 857713878 | E33: =D33/$D$16 -> 0.33721339 | F33: 1295017974 | G33: =F33/$F$16 -> 0.64576587 | H33: 1236176825 | I33: =H33/$H$16 -> 0.63063029 | J33: 1030583696 | K33: =J33/$J$16 -> 0.58526682
A34: Total equity and liabilities | B34: 495267208 | C34: =B34/$B$16 -> 0.19848263 | D34: 3543534495 | E34: =D34/$D$16 -> 1.3931537 | F34: 2005398601 | G34: =F34/$F$16 -> 1 | H34: 1960224320 | I34: =H34/$H$16 -> 1 | J34: 1760878385 | K34: =J34/$J$16 -> 1

Sheet Horizontal Analysis(BS) of DBP
A1: Balance Sheet of Deshbandhu Polymer Limited Horizontal Analysis
A3: Particulars | B3: 2022 | C3: Horizontal Analysis | D3: 2021 | E3: Horizontal Analysis | F3: 2020 | G3: Horizontal Analysis | H3: 2019 | I3: Horizontal Analysis | J3: 2018
A4: Property, plant and equipment | B4: 1015509672 | C4: =(B4-D4)/D4 -> -0.015222013 | D4: 1031206714 | E4: =(D4-F4)/F4 -> 1.24361 | F4: 459619411 | G4: =(F4-H4)/H4 -> 0.040814079 | H4: 441596074 | I4: =(H4-J4)/J4 -> -0.14242706 | J4: 514937045
A5: Investments | B5: 824901 | C5: =(B5-D5)/D5 -> -0.060344513 | D5: 877876 | E5: =(D5-F5)/F5 -> 0.22449674 | F5: 716928 | G5: =(F5-H5)/H5 -> 0 | H5: 716928 | I5: =(H5-J5)/J5 -> 0 | J5: 716928
A6: Accumulated Depreciation | B6: - | C6: - | D6: - | E6: - | F6: - | G6: - | H6: - | I6: - | J6: -160511475
A7: Total Non-current assets | B7: 1016334574 | C7: =(B7-D7)/D7 -> -0.015260394 | D7: 1032084591 | E7: =(D7-F7)/F7 -> 1.2420229 | F7: 460336339 | G7: =(F7-H7)/H7 -> 0.040747925 | H7: 442313002 | I7: =(H7-J7)/J7 -> 0.24545219 | J7: 355142498
A8: Inventories | B8: 401412927 | C8: =(B8-D8)/D8 -> 0.40869891 | D8: 284952963 | E8: =(D8-F8)/F8 -> 0.010017712 | F8: 282126699 | G8: =(F8-H8)/H8 -> 0.2795371 | H8: 220491223 | I8: =(H8-J8)/J8 -> 0.53628115 | J8: 143522703
A9: AccOUnt Receivables | B9: 298283337 | C9: =(B9-D9)/D9 -> 0.029469178 | D9: 289744796 | E9: =(D9-F9)/F9 -> 0.10396791 | F9: 262457625 | G9: =(F9-H9)/H9 -> -0.018132616 | H9: 267304556 | I9: =(H9-J9)/J9 -> -0.10994499 | J9: 300323635
A10: Inventories in transit | B10: 188710823 | C10: =(B10-D10)/D10 -> 0.0022185946 | D10: 188293077 | E10: =(D10-F10)/F10 -> -0.38436469 | F10: 305851655 | G10: =(F10-H10)/H10 -> -0.31474066 | H10: 446329786 | I10: =(H10-J10)/J10 -> 0.1938598 | J10: 373854439
A11: Inter comnany receivable | B11: - | C11: - | D11: 171378178 | E11: =(D11-F11)/F11 -> -0.21941885 | F11: 219552032 | G11: =(F11-H11)/H11 -> 0.38436234 | H11: 158594340 | I11: =(H11-J11)/J11 -> -0.1139359 | J11: 178987434
A12: Advances, deposits and prepayments | B12: 215347109 | C12: =(B12-D12)/D12 -> -0.038933065 | D12: 224070875 | E12: =(D12-F12)/F12 -> 0.35543802 | F12: 165312520 | G12: =(F12-H12)/H12 -> 0.16583602 | H12: 141797403 | I12: =(H12-J12)/J12 -> -0.16537007 | J12: 169892545
A13: Advance Income tax | B13: 361213480 | C13: =(B13-D13)/D13 -> 0.10785611 | D13: 326047287 | E13: =(D13-F13)/F13 -> 0.11992813 | F13: 291132330 | G13: =(F13-H13)/H13 -> 0.14105075 | H13: 255144068 | I13: =(H13-J13)/J13 -> 0.14255002 | J13: 223311071
A14: Cash and cash equivalents | B14: 13964956 | C14: =(B14-D14)/D14 -> -0.48206308 | D14: 26962658 | E14: =(D14-F14)/F14 -> 0.44731757 | F14: 18629400 | G14: =(F14-H14)/H14 -> -0.34055084 | H14: 28249941 | I14: =(H14-J14)/J14 -> 0.78299864 | J14: 15844062
A15: Total Currant assets | B15: 1478932632 | C15: =(B15-D15)/D15 -> -0.021513914 | D15: 1511449834 | E15: =(D15-F15)/F15 -> -0.02175474 | F15: 1545062262 | G15: =(F15-H15)/H15 -> 0.017887042 | H15: 1517911318 | I15: =(H15-J15)/J15 -> 0.079798367 | J15: 1405735889
A16: Total assets | B16: 2495267206 | C16: =(B16-D16)/D16 -> -0.018976436 | D16: 2543534425 | E16: =(D16-F16)/F16 -> 0.26834357 | F16: 2005398601 | G16: =(F16-H16)/H16 -> 0.023045465 | H16: 1960224320 | I16: =(H16-J16)/J16 -> 0.11320823 | J16: 1760878387
A17: Stated canital | B17: 613651500 | C17: =(B17-D17)/D17 -> 0 | D17: 613651500 | E17: =(D17-F17)/F17 -> 0 | F17: 613651500 | G17: =(F17-H17)/H17 -> 0 | H17: 613651500 | I17: =(H17-J17)/J17 -> 0 | J17: 613651500
A18: Revaluation Reserve | B18: 467003358 | C18: =(B18-D18)/D18 -> -0.013725378 | D18: 473502357 | E18: - | F18: - | G18: - | H18: - | I18: - | J18: -
A19: Retained Earnings | B19: 36712385 | C19: =(B19-D19)/D19 -> 0.70995404 | D19: 21469808 | E19: =(D19-F19)/F19 -> -0.27801519 | F19: 29737202 | G19: =(F19-H19)/H19 -> -0.32270771 | H19: 43906010 | I19: =(H19-J19)/J19 -> -0.04230573 | J19: 45845539
A20: Equity attributable to owners or the company | B20: 1117367243 | C20: =(B20-D20)/D20 -> 0.0078868766 | D20: 1108623665 | E20: =(D20-F20)/F20 -> 0.72310092 | F20: 643388702 | G20: =(F20-H20)/H20 -> -0.021547633 | H20: 657557510 | I20: =(H20-J20)/J20 -> -0.0029409215 | J20: 659497039
A21: Total equity | B21: 1117367243 | C21: =(B21-D21)/D21 -> 0.0078868766 | D21: 1108623665 | E21: =(D21-F21)/F21 -> 0.72310092 | F21: 643388702 | G21: =(F21-H21)/H21 -> -0.021547633 | H21: 657557510 | I21: =(H21-J21)/J21 -> -0.0029409215 | J21: 659497039
A22: Long Term Borrowings/Loan | B22: 375172771 | C22: =(B22-D22)/D22 -> -0.086859335 | D22: 410859778 | E22: - | F22: - | G22: - | H22: - | I22: - | J22: -
A23: Defferred Tax Liabilities | B23: 157771520 | C23: =(B23-D23)/D23 -> -0.051495324 | D23: 166337103 | E23: =(D23-F23)/F23 -> 1.4829165 | F23: 66992628 | G23: =(F23-H23)/H23 -> 0.0075596799 | H23: 66489985 | I23: =(H23-J23)/J23 -> -0.060844746 | J23: 70797650
A24: Total Non-current liabilities | B24: 532944291 | C24: =(B24-D24)/D24 -> -0.076668103 | D24: 577196881 | E24: =(D24-F24)/F24 -> 7.6158268 | F24: 66992628 | G24: =(F24-H24)/H24 -> 0.0075596799 | H24: 66489985 | I24: =(H24-J24)/J24 -> -0.060844746 | J24: 70797650
A25: Short-term borrowings - secured | B25: 552345251 | C25: =(B25-D25)/D25 -> 0.029813143 | D25: 536354828 | E25: =(D25-F25)/F25 -> -0.46084662 | F25: 994809360 | G25: =(F25-H25)/H25 -> 0.084661645 | H25: 917161001 | I25: =(H25-J25)/J25 -> 0.27809407 | J25: 717600546
A26: Other Pavable | B26: 50423520 | C26: =(B26-D26)/D26 -> -0.26468731 | D26: 68574255 | E26: =(D26-F26)/F26 -> 6.4523155 | F26: 9201738 | G26: =(F26-H26)/H26 -> -0.35906932 | H26: 14356838 | I26: =(H26-J26)/J26 -> 0.78579764 | J26: 8039454
A27: Bank overdraft | B27: 214972098 | C27: =(B27-D27)/D27 -> -0.085580462 | D27: 235091322 | E27: =(D27-F27)/F27 -> 0.081045586 | F27: 217466613 | G27: =(F27-H27)/H27 -> -0.073211827 | H27: 234645434 | I27: =(H27-J27)/J27 -> -0.024986255 | J27: 240658591
A28: Workers' Profit Participation Fund | B28: 1342061 | C28: =(B28-D28)/D28 -> 1.8176268 | D28: 476309 | E28: =(D28-F28)/F28 -> -0.78538656 | F28: 2219381 | G28: =(F28-H28)/H28 -> 0.36239837 | H28: 1629025 | I28: =(H28-J28)/J28 -> -0.25570945 | J28: 2188695
A29: Accounts and other payable | B29: 1739657 | C29: =(B29-D29)/D29 -> -0.24120717 | D29: 2292664 | E29: =(D29-F29)/F29 -> -0.36034186 | F29: 3584202 | G29: =(F29-H29)/H29 -> -0.37450163 | H29: 5730154 | I29: =(H29-J29)/J29 -> -0.24483643 | J29: 7587964
A30: share money refundable | B30: 14924500 | C30: =(B30-D30)/D30 -> 0 | D30: 14924500 | E30: =(D30-F30)/F30 -> 0 | F30: 14924500 | G30: =(F30-H30)/H30 -> 0 | H30: 14924500 | I30: =(H30-J30)/J30 -> 0 | J30: 14924500
A31: Provision for Tax I abilities/ Current Tax I ability | B31: - | C31: - | D31: - | E31: - | F31: 52811477 | G31: =(F31-H31)/H31 -> 0.10648445 | H31: 47729073 | I31: =(H31-J31)/J31 -> 0.20576844 | J31: 39583946
A32: Unclaimed Dividend | B32: 9208586 | C32: - | D32: - | E32: - | F32: - | G32: - | H32: - | I32: - | J32: -
A33: Total Current liabilities | B33: 844955673 | C33: =(B33-D33)/D33 -> -0.014874663 | D33: 857713878 | E33: =(D33-F33)/F33 -> -0.33768187 | F33: 1295017974 | G33: =(F33-H33)/H33 -> 0.047599298 | H33: 1236176825 | I33: =(H33-J33)/J33 -> 0.19949193 | J33: 1030583696
A34: Total equity and liabilities | B34: 495267208 | C34: =(B34-D34)/D34 -> -0.86023356 | D34: 3543534495 | E34: =(D34-F34)/F34 -> 0.76699759 | F34: 2005398601 | G34: =(F34-H34)/H34 -> 0.023045465 | H34: 1960224320 | I34: =(H34-J34)/J34 -> 0.11320824 | J34: 1760878385

Sheet IS of DBP
A1: Income Statements of Deshbandhu Polymer Limited
A4: Particulars | C4: 2022 | D4: 2021 | E4: 2020 | F4: 2019 | G4: 2018
A5: Turnover | C5: 1046562186 | D5: 773807394 | E5: 824577244 | F5: 799252742 | G5: 945699450
A6: Cost of sales | C6: 918031857 | D6: 682505268 | E6: 729930375 | F6: 682695931 | G6: 818873316
A7: Gross profit | C7: 128530329 | D7: 91302126 | E7: 94646869 | F7: 116556811 | G7: 126826134
A8: Operating expenses | C8: 21342104 | D8: 24165994 | E8: 24176366 | F8: 27941040 | G8: 34132822
A9: Selling & Distribution expenses | C9: 5004255 | D9: 9261265 | E9: 8945103 | F9: 10219725 | G9: 13510565
A10: Administrative expenses | C10: 16337849 | D10: 14904729 | E10: 15231263 | F10: 17721315 | G10: 20622257
A11: Operating profit | C11: 107188224 | D11: 67136131 | E11: 70470503 | F11: 88615771 | G11: 92693312
A12: Finance income | C12: 5744046 | D12: 21908703 | E12: 22489886 | F12: 16236492 | G12: 11497138
A13: Finance costs | C13: 84748996 | D13: 79042355 | E13: 80562913 | F13: 70642730 | G13: 58277847
A14: Profit before contribution to workers' profit participation fund | C14: 28183274 | D14: 10002479 | E14: 12397476 | F14: 34209533 | G14: 45912603
A15: Contribution to workers' profit participation fund | C15: 1342061 | D15: 476309 | E15: 590357 | F15: 1629025 | G15: 2188695
... A17: Income tax expense | C17: 2251746 | D17: 2378114 | E17: 5585045 | F17: 3837462 | G17: -9355054
A18: Current Tax | C18: -6313837 | D18: -4774297 | E18: 5082402 | F18: (8,145, 127.00) | G18: -10943477
A19: Deferred Tax | C19: 8555582 | D19: 7152410 | E19: 502643 | F19: 4307665 | G19: 1588423
A20: Profit after tax | C20: 29092959 | D20: 11904284 | E20: 6222074 | F20: 28743046 | G20: 53078962
A21: Earnings Per Share (EPS) | C21: 0.47 | D21: 0.2 | E21: 0.1 | G21: 0.56

Sheet Vertical Analysis(IS) of DBP
A1: Income Statements of Deshbandhu Polymer Limited (Vertical Analysis)
A4: Particulars | B4: 2022 | C4: Vertical Analysis | D4: 2021 | E4: Vertical Analysis | F4: 2020 | G4: Vertical Analysis | H4: 2019 | I4: Vertical Analysis | J4: 2018 | K4: Vertical Analysis
A5: Turnover | B5: 1046562186 | C5: =B5/$B$5 -> 1 | D5: 773807394 | E5: =D5/$D$5 -> 1 | F5: 824577244 | G5: =F5/$F$5 -> 1 | H5: 799252742 | I5: =H5/$H$5 -> 1 | J5: 945699450 | K5: =J5/$J$5 -> 1
A6: Cost of sales | B6: 918031857 | C6: =B6/$B$5 -> 0.87718806 | D6: 682505268 | E6: =D6/$D$5 -> 0.88200924 | F6: 729930375 | G6: =F6/$F$5 -> 0.8852177 | H6: 682695931 | I6: =H6/$H$5 -> 0.85416777 | J6: 818873316 | K6: =J6/$J$5 -> 0.86589171
A7: Gross profit | B7: 128530329 | C7: =B7/$B$5 -> 0.12281194 | D7: 91302126 | E7: =D7/$D$5 -> 0.11799076 | F7: 94646869 | G7: =F7/$F$5 -> 0.1147823 | H7: 116556811 | I7: =H7/$H$5 -> 0.14583223 | J7: 126826134 | K7: =J7/$J$5 -> 0.13410829
A8: Operating expenses | B8: 21342104 | C8: =B8/$B$5 -> 0.020392581 | D8: 24165994 | E8: =D8/$D$5 -> 0.031229986 | F8: 24176366 | G8: =F8/$F$5 -> 0.02931971 | H8: 27941040 | I8: =H8/$H$5 -> 0.034958954 | J8: 34132822 | K8: =J8/$J$5 -> 0.036092674
A9: Selling & Distribution expenses | B9: 5004255 | C9: =B9/$B$5 -> 0.0047816127 | D9: 9261265 | E9: =D9/$D$5 -> 0.011968437 | F9: 8945103 | G9: =F9/$F$5 -> 0.010848108 | H9: 10219725 | I9: =H9/$H$5 -> 0.0127866 | J9: 13510565 | K9: =J9/$J$5 -> 0.01428632
A10: Administrative expenses | B10: 16337849 | C10: =B10/$B$5 -> 0.015610968 | D10: 14904729 | E10: =D10/$D$5 -> 0.019261549 | F10: 15231263 | G10: =F10/$F$5 -> 0.018471602 | H10: 17721315 | I10: =H10/$H$5 -> 0.022172354 | J10: 20622257 | K10: =J10/$J$5 -> 0.021806354
A11: Operating profit | B11: 107188224 | C11: =B11/$B$5 -> 0.10241935 | D11: 67136131 | E11: =D11/$D$5 -> 0.086760777 | F11: 70470503 | G11: =F11/$F$5 -> 0.085462585 | H11: 88615771 | I11: =H11/$H$5 -> 0.11087328 | J11: 92693312 | K11: =J11/$J$5 -> 0.098015614
A12: Finance income | B12: 5744046 | C12: =B12/$B$5 -> 0.0054884899 | D12: 21908703 | E12: =D12/$D$5 -> 0.028312863 | F12: 22489886 | G12: =F12/$F$5 -> 0.027274444 | H12: 16236492 | I12: =H12/$H$5 -> 0.02031459 | J12: 11497138 | K12: =J12/$J$5 -> 0.012157285
A13: Finance costs | B13: 84748996 | C13: =B13/$B$5 -> 0.080978462 | D13: 79042355 | E13: =D13/$D$5 -> 0.10214732 | F13: 80562913 | G13: =F13/$F$5 -> 0.097702081 | H13: 70642730 | I13: =H13/$H$5 -> 0.088385971 | J13: 58277847 | K13: =J13/$J$5 -> 0.061624068
A14: Profit before contribution to workers' profit participation fund | B14: 28183274 | C14: =B14/$B$5 -> 0.026929383 | D14: 10002479 | E14: =D14/$D$5 -> 0.012926316 | F14: 12397476 | G14: =F14/$F$5 -> 0.015034948 | H14: 34209533 | I14: =H14/$H$5 -> 0.042801896 | J14: 45912603 | K14: =J14/$J$5 -> 0.048548831
A15: Contribution to workers' profit participation fund | B15: 1342061 | C15: =B15/$B$5 -> 0.0012823519 | D15: 476309 | E15: =D15/$D$5 -> 0.00061553948 | F15: 590357 | G15: =F15/$F$5 -> 0.00071595112 | H15: 1629025 | I15: =H15/$H$5 -> 0.0020381851 | J15: 2188695 | K15: =J15/$J$5 -> 0.0023143664
A16: Profit before taxatior | B16: 26841213 | C16: =B16/$B$5 -> 0.025647031 | D16: 9526170 | E16: =D16/$D$5 -> 0.012310777 | F16: 11807118 | G16: =F16/$F$5 -> 0.014318996 | H16: 32580507 | I16: =H16/$H$5 -> 0.04076371 | J16: 43723908 | K16: =J16/$J$5 -> 0.046234465
A17: Income tax expense | B17: 2251746 | C17: =B17/$B$5 -> 0.0021515645 | D17: 2378114 | E17: =D17/$D$5 -> 0.0030732635 | F17: 5585045 | G17: =F17/$F$5 -> 0.0067732223 | H17: 3837462 | I17: =H17/$H$5 -> 0.0048013123 | J17: -9355054 | K17: =J17/$J$5 -> -0.0098922062
A18: Current Tax | B18: -6313837 | C18: =B18/$B$5 -> -0.0060329306 | D18: -4774297 | E18: =D18/$D$5 -> -0.0061698777 | F18: 5082402 | G18: =F18/$F$5 -> 0.0061636457 | H18: (8,145, 127.00) | I18: - | J18: -10943477 | K18: =J18/$J$5 -> -0.011571834
A19: Deferred Tax | B19: 8555582 | C19: =B19/$B$5 -> 0.008174939 | D19: 7152410 | E19: =D19/$D$5 -> 0.0092431399 | F19: 502643 | G19: =F19/$F$5 -> 0.00060957661 | H19: 4307665 | I19: =H19/$H$5 -> 0.0053896155 | J19: 1588423 | K19: =J19/$J$5 -> 0.0016796277
A20: Profit after tax | B20: 29092959 | C20: =B20/$B$5 -> 0.027798596 | D20: 11904284 | E20: =D20/$D$5 -> 0.01538404 | F20: 6222074 | G20: =F20/$F$5 -> 0.0075457746 | H20: 28743046 | I20: =H20/$H$5 -> 0.035962399 | J20: 53078962 | K20: =J20/$J$5 -> 0.056126671
A21: Earnings Per Share (EPS) | B21: 0.47 | C21: =B21/$B$5 -> 4.4908942e-10 | D21: 0.2 | E21: =D21/$D$5 -> 2.5846225e-10 | F21: 0.1 | G21: =F21/$F$5 -> 1.2127427e-10 | I21: =H21/$H$5 -> 0 | J21: 0.56 | K21: =J21/$J$5 -> 5.921543e-10

Sheet Horizontal Analysis(IS) of DBP
A1: Income Statements of Deshbandhu Polymer Limited (Horizontal Analysis)
A4: Particulars | B4: 2022 | C4: Horizontal Analysis | D4: 2021 | E4: Horizontal Analysis | F4: 2020 | G4: Horizontal Analysis | H4: 2019 | I4: Horizontal Analysis | J4: 2018
A5: Turnover | B5: 1046562186 | C5: =(B5-D5)/D5 -> 0.35248409 | D5: 773807394 | E5: =(D5-F5)/F5 -> -0.061570763 | F5: 824577244 | G5: =(F5-H5)/H5 -> 0.031685224 | H5: 799252742 | I5: =(H5-J5)/J5 -> -0.15485544 | J5: 945699450
A6: Cost of sales | B6: 918031857 | C6: =(B6-D6)/D6 -> 0.34509124 | D6: 682505268 | E6: =(D6-F6)/F6 -> -0.064972097 | F6: 729930375 | G6: =(F6-H6)/H6 -> 0.069188114 | H6: 682695931 | I6: =(H6-J6)/J6 -> -0.16629848 | J6: 818873316
A7: Gross profit | B7: 128530329 | C7: =(B7-D7)/D7 -> 0.40774738 | D7: 91302126 | E7: =(D7-F7)/F7 -> -0.035339183 | F7: 94646869 | G7: =(F7-H7)/H7 -> -0.18797651 | H7: 116556811 | I7: =(H7-J7)/J7 -> -0.080971663 | J7: 126826134
A8: Operating expenses | B8: 21342104 | C8: =(B8-D8)/D8 -> -0.11685387 | D8: 24165994 | E8: =(D8-F8)/F8 -> -0.00042901402 | F8: 24176366 | G8: =(F8-H8)/H8 -> -0.13473636 | H8: 27941040 | I8: =(H8-J8)/J8 -> -0.18140258 | J8: 34132822
A9: Selling & Distribution expenses | B9: 5004255 | C9: =(B9-D9)/D9 -> -0.45965751 | D9: 9261265 | E9: =(D9-F9)/F9 -> 0.035344702 | F9: 8945103 | G9: =(F9-H9)/H9 -> -0.12472175 | H9: 10219725 | I9: =(H9-J9)/J9 -> -0.24357531 | J9: 13510565
A10: Administrative expenses | B10: 16337849 | C10: =(B10-D10)/D10 -> 0.096152033 | D10: 14904729 | E10: =(D10-F10)/F10 -> -0.021438406 | F10: 15231263 | G10: =(F10-H10)/H10 -> -0.14051169 | H10: 17721315 | I10: =(H10-J10)/J10 -> -0.14067044 | J10: 20622257
A11: Operating profit | B11: 107188224 | C11: =(B11-D11)/D11 -> 0.5965803 | D11: 67136131 | E11: =(D11-F11)/F11 -> -0.047315854 | F11: 70470503 | G11: =(F11-H11)/H11 -> -0.20476342 | H11: 88615771 | I11: =(H11-J11)/J11 -> -0.043989592 | J11: 92693312
A12: Finance income | B12: 5744046 | C12: =(B12-D12)/D12 -> -0.73781898 | D12: 21908703 | E12: =(D12-F12)/F12 -> -0.025841972 | F12: 22489886 | G12: =(F12-H12)/H12 -> 0.3851444 | H12: 16236492 | I12: =(H12-J12)/J12 -> 0.41222033 | J12: 11497138
A13: Finance costs | B13: 84748996 | C13: =(B13-D13)/D13 -> 0.072197254 | D13: 79042355 | E13: =(D13-F13)/F13 -> -0.018874169 | F13: 80562913 | G13: =(F13-H13)/H13 -> 0.14042751 | H13: 70642730 | I13: =(H13-J13)/J13 -> 0.21217124 | J13: 58277847
A14: Profit before contribution to workers' profit participation fund | B14: 28183274 | C14: =(B14-D14)/D14 -> 1.8176289 | D14: 10002479 | E14: =(D14-F14)/F14 -> -0.19318424 | F14: 12397476 | G14: =(F14-H14)/H14 -> -0.63760172 | H14: 34209533 | I14: =(H14-J14)/J14 -> -0.25489886 | J14: 45912603
A15: Contribution to workers' profit participation fund | B15: 1342061 | C15: =(B15-D15)/D15 -> 1.8176268 | D15: 476309 | E15: =(D15-F15)/F15 -> -0.1931848 | F15: 590357 | G15: =(F15-H15)/H15 -> -0.63760102 | H15: 1629025 | I15: =(H15-J15)/J15 -> -0.25570945 | J15: 2188695
A16: Profit before taxatior | B16: 26841213 | C16: =(B16-D16)/D16 -> 1.817629 | D16: 9526170 | E16: =(D16-F16)/F16 -> -0.19318415 | F16: 11807118 | G16: =(F16-H16)/H16 -> -0.63760177 | H16: 32580507 | I16: =(H16-J16)/J16 -> -0.2548583 | J16: 43723908
A17: Income tax expense | B17: 2251746 | C17: =(B17-D17)/D17 -> -0.053137907 | D17: 2378114 | E17: =(D17-F17)/F17 -> -0.57419967 | F17: 5585045 | G17: =(F17-H17)/H17 -> 0.45540073 | H17: 3837462 | I17: =(H17-J17)/J17 -> -1.410202 | J17: -9355054
A18: Current Tax | B18: -6313837 | C18: =(B18-D18)/D18 -> 0.32246423 | D18: -4774297 | E18: =(D18-F18)/F18 -> -1.9393781 | F18: 5082402 | G18: - | H18: (8,145, 127.00) | I18: - | J18: -10943477
A19: Deferred Tax | B19: 8555582 | C19: =(B19-D19)/D19 -> 0.19618171 | D19: 7152410 | E19: =(D19-F19)/F19 -> 13.229602 | F19: 502643 | G19: =(F19-H19)/H19 -> -0.88331428 | H19: 4307665 | I19: =(H19-J19)/J19 -> 1.711913 | J19: 1588423
A20: Profit after tax | B20: 29092959 | C20: =(B20-D20)/D20 -> 1.4439067 | D20: 11904284 | E20: =(D20-F20)/F20 -> 0.91323408 | F20: 6222074 | G20: =(F20-H20)/H20 -> -0.78352767 | H20: 28743046 | I20: =(H20-J20)/J20 -> -0.45848515 | J20: 53078962
A21: Earnings Per Share (EPS) | B21: 0.47 | C21: =(B21-D21)/D21 -> 1.35 | D21: 0.2 | E21: =(D21-F21)/F21 -> 1 | F21: 0.1 | G21: - | I21: =(H21-J21)/J21 -> -1 | J21: 0.56

Sheet Ratio Analysis
G2: Ratio Analysis of Deshbandhu Polymer Limited
G4: Ratio Name | I4: 2022 | J4: 2021 | K4: 2020 | L4: 2019 | M4: 2018
G6: Liquidity Ratio:
G8: Current Ratio | I8: ='BS of DBP'!C15/'BS of DBP'!C33 -> 1.750308 | J8: ='BS of DBP'!D15/'BS of DBP'!D33 -> 1.7621842 | K8: ='BS of DBP'!E15/'BS of DBP'!E33 -> 1.1930817 | L8: ='BS of DBP'!F15/'BS of DBP'!F33 -> 1.2279079 | M8: ='BS of DBP'!G15/'BS of DBP'!G33 -> 1.3640191
G9: Quick Ratio | I9: =('BS of DBP'!C9+'BS of DBP'!C14)/'BS of DBP'!C33 -> 0.36954399 | J9: =('BS of DBP'!D9+'BS of DBP'!D14)/'BS of DBP'!D33 -> 0.36924604 | K9: =('BS of DBP'!E9+'BS of DBP'!E14)/'BS of DBP'!E33 -> 0.21705261 | L9: =('BS of DBP'!F9+'BS of DBP'!F14)/'BS of DBP'!F33 -> 0.23908756 | M9: =('BS of DBP'!G9+'BS of DBP'!G14)/'BS of DBP'!G33 -> 0.30678508
G10: Account Receivable Turnover | I10: ='IS of DBP'!C5/(('BS of DBP'!C9+'BS of DBP'!D9)/2) -> 3.559565 | J10: ='IS of DBP'!D5/(('BS of DBP'!D9+'BS of DBP'!E9)/2) -> 2.8026222 | K10: ='IS of DBP'!E5/(('BS of DBP'!E9+'BS of DBP'!F9)/2) -> 3.1130091 | L10: ='IS of DBP'!F5/(('BS of DBP'!F9+'BS of DBP'!G9)/2) -> 2.8161136 | M10: ='IS of DBP'!G5/(('BS of DBP'!G9+'BS of DBP'!H9)/2) -> 6.297869
G11: Average Collection Period | I11: =365/I10 -> 102.54062 | J11: =365/J10 -> 130.23518 | K11: =365/K10 -> 117.2499 | L11: =365/L10 -> 129.61125 | M11: =365/M10 -> 57.956112
G12: Inventory Turnover | I12: ='IS of DBP'!C6/(('BS of DBP'!C8+'BS of DBP'!D8)/2) -> 2.6750509 | J12: ='IS of DBP'!D6/(('BS of DBP'!D8+'BS of DBP'!E8)/2) -> 2.4070878 | K12: ='IS of DBP'!E6/(('BS of DBP'!E8+'BS of DBP'!F8)/2) -> 2.9045139 | L12: ='IS of DBP'!F6/(('BS of DBP'!F8+'BS of DBP'!G8)/2) -> 3.750933 | M12: ='IS of DBP'!G6/(('BS of DBP'!G8+'BS of DBP'!H8)/2) -> 11.411063
G13: Days in Inventory | I13: =365/I12 -> 136.446 | J13: =365/J12 -> 151.63552 | K13: =365/K12 -> 125.66647 | L13: =365/L12 -> 97.309122 | M13: =365/M12 -> 31.986502
G15: Profitability Ratio:
G17: Profit margin | I17: ='IS of DBP'!C20/'IS of DBP'!C5 -> 0.027798596 | J17: ='IS of DBP'!D20/'IS of DBP'!D5 -> 0.01538404 | K17: ='IS of DBP'!E20/'IS of DBP'!E5 -> 0.0075457746 | L17: ='IS of DBP'!F20/'IS of DBP'!F5 -> 0.035962399 | M17: ='IS of DBP'!G20/'IS of DBP'!G5 -> 0.056126671
G18: Asset Turnover | I18: ='IS of DBP'!C5/(('BS of DBP'!C16+'BS of DBP'!D16)/2) -> 0.41540123 | J18: ='IS of DBP'!D5/(('BS of DBP'!D16+'BS of DBP'!E16)/2) -> 0.3402149 | K18: ='IS of DBP'!E5/(('BS of DBP'!E16+'BS of DBP'!F16)/2) -> 0.41586266 | L18: ='IS of DBP'!F5/(('BS of DBP'!F16+'BS of DBP'!G16)/2) -> 0.42957844 | M18: ='IS of DBP'!G5/(('BS of DBP'!G16+'BS of DBP'!H16)/2) -> 1.0741224
G19: Earning Per Share(EPS) | I19: 0.47 | J19: 0.2 | K19: 0.1 | L19: 0.47 | M19: 0.56
G20: Retrun on Asset | I20: ='IS of DBP'!C20/(('BS of DBP'!C16+'BS of DBP'!D16)/2) -> 0.011547571 | J20: ='IS of DBP'!D20/(('BS of DBP'!D16+'BS of DBP'!E16)/2) -> 0.0052338797 | K20: ='IS of DBP'!E20/(('BS of DBP'!E16+'BS of DBP'!F16)/2) -> 0.0031380059 | L20: ='IS of DBP'!F20/(('BS of DBP'!F16+'BS of DBP'!G16)/2) -> 0.015448671 | M20: ='IS of DBP'!G20/(('BS of DBP'!G16+'BS of DBP'!H16)/2) -> 0.060286914
G21: Price Earning Ratio | I21: ='BS of DBP'!C35/'Ratio Analysis'!I19 -> 38.510638 | J21: ='BS of DBP'!D35/'Ratio Analysis'!J19 -> 103 | K21: ='BS of DBP'!E35/'Ratio Analysis'!K19 -> 115.5 | L21: ='BS of DBP'!F35/'Ratio Analysis'!L19 -> 23.680851 | M21: ='BS of DBP'!G35/'Ratio Analysis'!M19 -> 25.678571
G24: Solvency Ratio:
G25: Debt to Asset Ratio | I25: =('BS of DBP'!C33+'BS of DBP'!C24)/'BS of DBP'!C16 -> 0.55220538 | J25: =('BS of DBP'!D33+'BS of DBP'!D24)/'BS of DBP'!D16 -> 0.56414049 | K25: =('BS of DBP'!E33+'BS of DBP'!E24)/'BS of DBP'!E16 -> 0.67917201 | L25: =('BS of DBP'!F33+'BS of DBP'!F24)/'BS of DBP'!F16 -> 0.66454987 | M25: =('BS of DBP'!G33+'BS of DBP'!G24)/'BS of DBP'!G16 -> 0.62547269
