Workbook

Sheet BS of DSBSL
A1: Balance Sheet of Dominage Steel Building Systems Limited
A4: Particulars | C4: 2022 | D4: 2021 | E4: 2020 | F4: 2019
A5: Property, plant and equipment | C5: 884774242 | D5: 805223543 | E5: 747219293 | F5: 694573079
A6: Right-of-Use (ROU) asset | C6: 1304962 | D6: 1444041 | E6: - | F6: -
A7: Projects in Progress (Non-Current Portion) | C7: 192689219 | D7: 221209585 | E7: 186376004 | F7: 178434246
A8: Capital Work in Progress | C8: 18208086 | D8: 11740030 | E8: 23948085 | F8: 17786355
A9: Total Non-current assets | C9: 1096976509 | D9: 1039617199 | E9: 957543382 | F9: 890793680
A10: inventores | C10: 357081053 | D10: 382727968 | E10: 379297787 | F10: 333405588
A11: Trade and other receivables | C11: 169136365 | D11: 175419813 | E11: 172049846 | F11: 186702573
A12: Advances, deposits and prepayments | C12: 185473547 | D12: 134271647 | E12: 126776065 | F12: 100947242
A13: Cash and cash equivalents | C13: 151001785 | D13: 292243893 | E13: 9348913 | F13: 18302860
A14: Total Current assets | C14: 862692750 | D14: 984663321 | E14: 687472611 | F14: 639358263
A15: Total assets | C15: 1959669259 | D15: 2024280521 | E15: 1645015993 | F15: 1530151943
A16: Stated canital | C16: 1026000000 | D16: 1026000000 | E16: 650000000 | F16: 650000000
A17: Retained Earninas | C17: 742298212 | D17: 722076338 | E17: 729751773 | F17: 637477371
A18: Equity attributable to owners of the company | C18: 1768298212 | D18: 1748076338 | E18: 1379751773 | F18: 1287477371
... A21: Dofferred Tay I isbilities | C21: 71550905 | D21: 56194224 | E21: 79036298 | F21: 69124828
A22: Lease liability (non-current portion)/ Finance Lease obligations- non-current portion/ Finance Lease Net off current portion | C22: 530250 | D22: 1009295 | E22: - | F22: -
A23: Total Non-current liabilities | C23: 96417910 | D23: 71844643 | E23: 84737876 | F23: 75226130
A24: Trade and other pavables | C24: 20754512 | D24: 19567570 | E24: 26254870 | F24: 39469462
A25: Accrued expenses/Provision for expenses/liability for expenses | C25: 2757081 | D25: 3273356 | E25: 2678504 | F25: 2844973
A26: Current portion of term lar | C26: 11452591 | D26: 7883682 | E26: 3818023 | F26: 6903467
A27: Short term loan | C27: 43008343 | D27: 47930689 | E27: 44335538 | F27: 41022820
A28: Income Tay Davable | C28: 11269878 | D28: 119142610 | E28: 96970007 | F28: 69767858
A29: Current portion of lease obligation/ Finance | C29: 482045 | D29: 444693 | E29: - | F29: -
A30: Morkorel Drofit Dorticinstion Curd | C30: 4029885 | D30: 5311555 | E30: 6469402 | F30: 7439862
A31: Dividend navable | C31: 1198802 | D31: 805386 | E31: - | F31: -
A32: Total Current liabilities | C32: 94953137 | D32: 204359541 | E32: 180526344 | F32: 167448442
A33: Total equity and liabilities | C33: 1959669259 | D33: 2024280521 | E33: 1645015993 | F33: 1530151943
A34: Market Price | C34: 21.02 | D34: 24.52 | E34: 34.45

Sheet Vertical(BS) of DSBSL
A1: Balance Sheet of Dominage Steel Building Systems Limited(Vertical Analysis)
A4: Particulars | B4: 2022 | C4: Vertical Analysis | D4: 2021 | E4: Vertical Analysis | F4: 2020 | G4: Vertical Analysis | H4: 2019 | I4: Vertical Analysis
A5: Property, plant and equipment | B5: 884774242 | C5: =B5/$B$15 -> 0.45149162 | D5: 805223543 | E5: =D5/$D$15 -> 0.39778259 | F5: 747219293 | G5: =F5/$F$15 -> 0.45423224 | H5: 694573079 | I5: =H5/$H$15 -> 0.45392425
A6: Right-of-Use (ROU) asset | B6: 1304962 | C6: =B6/$B$15 -> 0.00066590931 | D6: 1444041 | E6: =D6/$D$15 -> 0.00071336012 | F6: - | G6: - | H6: - | I6: -
A7: Projects in Progress (Non-Current Portion) | B7: 192689219 | C7: =B7/$B$15 -> 0.098327418 | D7: 221209585 | E7: =D7/$D$15 -> 0.10927813 | F7: 186376004 | G7: =F7/$F$15 -> 0.11329738 | H7: 178434246 | I7: =H7/$H$15 -> 0.11661211
A8: Capital Work in Progress | B8: 18208086 | C8: =B8/$B$15 -> 0.0092914077 | D8: 11740030 | E8: =D8/$D$15 -> 0.0057996063 | F8: 23948085 | G8: =F8/$F$15 -> 0.014557965 | H8: 17786355 | I8: =H8/$H$15 -> 0.011623914
A9: Total Non-current assets | B9: 1096976509 | C9: =B9/$B$15 -> 0.55977635 | D9: 1039617199 | E9: =D9/$D$15 -> 0.51357368 | F9: 957543382 | G9: =F9/$F$15 -> 0.58208758 | H9: 890793680 | I9: =H9/$H$15 -> 0.58216028
A10: inventores | B10: 357081053 | C10: =B10/$B$15 -> 0.18221496 | D10: 382727968 | E10: =D10/$D$15 -> 0.18906864 | F10: 379297787 | G10: =F10/$F$15 -> 0.23057392 | H10: 333405588 | I10: =H10/$H$15 -> 0.21789051
A11: Trade and other receivables | B11: 169136365 | C11: =B11/$B$15 -> 0.086308628 | D11: 175419813 | E11: =D11/$D$15 -> 0.086657858 | F11: 172049846 | G11: =F11/$F$15 -> 0.10458856 | H11: 186702573 | I11: =H11/$H$15 -> 0.12201571
A12: Advances, deposits and prepayments | B12: 185473547 | C12: =B12/$B$15 -> 0.094645332 | D12: 134271647 | E12: =D12/$D$15 -> 0.066330553 | F12: 126776065 | G12: =F12/$F$15 -> 0.077066767 | H12: 100947242 | I12: =H12/$H$15 -> 0.065972038
A13: Cash and cash equivalents | B13: 151001785 | C13: =B13/$B$15 -> 0.07705473 | D13: 292243893 | E13: =D13/$D$15 -> 0.14436927 | F13: 9348913 | G13: =F13/$F$15 -> 0.0056831745 | H13: 18302860 | I13: =H13/$H$15 -> 0.011961466
A14: Total Current assets | B14: 862692750 | C14: =B14/$B$15 -> 0.44022365 | D14: 984663321 | E14: =D14/$D$15 -> 0.48642632 | F14: 687472611 | G14: =F14/$F$15 -> 0.41791242 | H14: 639358263 | I14: =H14/$H$15 -> 0.41783972
A15: Total assets | B15: 1959669259 | C15: =B15/$B$15 -> 1 | D15: 2024280521 | E15: =D15/$D$15 -> 1 | F15: 1645015993 | G15: =F15/$F$15 -> 1 | H15: 1530151943 | I15: =H15/$H$15 -> 1
A16: Stated canital | B16: 1026000000 | C16: =B16/$B$15 -> 0.52355774 | D16: 1026000000 | E16: =D16/$D$15 -> 0.50684675 | F16: 650000000 | G16: =F16/$F$15 -> 0.39513294 | H16: 650000000 | I16: =H16/$H$15 -> 0.42479442
A17: Retained Earninas | B17: 742298212 | C17: =B17/$B$15 -> 0.3787875 | D17: 722076338 | E17: =D17/$D$15 -> 0.35670765 | F17: 729751773 | G17: =F17/$F$15 -> 0.44361379 | H17: 637477371 | I17: =H17/$H$15 -> 0.4166105
A18: Equity attributable to owners of the company | B18: 1768298212 | C18: =B18/$B$15 -> 0.90234523 | D18: 1748076338 | E18: =D18/$D$15 -> 0.86355439 | F18: 1379751773 | G18: =F18/$F$15 -> 0.83874672 | H18: 1287477371 | I18: =H18/$H$15 -> 0.84140492
... A21: Dofferred Tay I isbilities | B21: 71550905 | C21: =B21/$B$15 -> 0.036511725 | D21: 56194224 | E21: =D21/$D$15 -> 0.027760097 | F21: 79036298 | G21: =F21/$F$15 -> 0.048045915 | H21: 69124828 | I21: =H21/$H$15 -> 0.04517514
A22: Lease liability (non-current portion)/ Finance Lease obligations- non-current portion/ Finance Lease Net off current portion | B22: 530250 | C22: =B22/$B$15 -> 0.00027058137 | D22: 1009295 | E22: =D22/$D$15 -> 0.00049859443 | F22: - | G22: - | H22: - | I22: -
A23: Total Non-current liabilities | B23: 96417910 | C23: =B23/$B$15 -> 0.049201114 | D23: 71844643 | E23: =D23/$D$15 -> 0.035491446 | F23: 84737876 | G23: =F23/$F$15 -> 0.051511886 | H23: 75226130 | I23: =H23/$H$15 -> 0.049162523
A24: Trade and other pavables | B24: 20754512 | C24: =B24/$B$15 -> 0.010590824 | D24: 19567570 | E24: =D24/$D$15 -> 0.009666432 | F24: 26254870 | G24: =F24/$F$15 -> 0.015960252 | H24: 39469462 | I24: =H24/$H$15 -> 0.025794472
A25: Accrued expenses/Provision for expenses/liability for expenses | B25: 2757081 | C25: =B25/$B$15 -> 0.0014069114 | D25: 3273356 | E25: =D25/$D$15 -> 0.0016170466 | F25: 2678504 | G25: =F25/$F$15 -> 0.0016282541 | H25: 2844973 | I25: =H25/$H$15 -> 0.0018592748
A26: Current portion of term lar | B26: 11452591 | C26: =B26/$B$15 -> 0.0058441448 | D26: 7883682 | E26: =D26/$D$15 -> 0.00389456 | F26: 3818023 | G26: =F26/$F$15 -> 0.0023209641 | H26: 6903467 | I26: =H26/$H$15 -> 0.0045116219
A27: Short term loan | B27: 43008343 | C27: =B27/$B$15 -> 0.021946736 | D27: 47930689 | E27: =D27/$D$15 -> 0.023677889 | F27: 44335538 | G27: =F27/$F$15 -> 0.026951433 | H27: 41022820 | I27: =H27/$H$15 -> 0.026809638
A28: Income Tay Davable | B28: 11269878 | C28: =B28/$B$15 -> 0.0057509082 | D28: 119142610 | E28: =D28/$D$15 -> 0.058856768 | F28: 96970007 | G28: =F28/$F$15 -> 0.058947759 | H28: 69767858 | I28: =H28/$H$15 -> 0.045595379
A29: Current portion of lease obligation/ Finance | B29: 482045 | C29: =B29/$B$15 -> 0.00024598284 | D29: 444693 | E29: =D29/$D$15 -> 0.00021967953 | F29: - | G29: - | H29: - | I29: -
A30: Morkorel Drofit Dorticinstion Curd | B30: 4029885 | C30: =B30/$B$15 -> 0.0020564108 | D30: 5311555 | E30: =D30/$D$15 -> 0.0026239224 | F30: 6469402 | G30: =F30/$F$15 -> 0.0039327289 | H30: 7439862 | I30: =H30/$H$15 -> 0.004862172
A31: Dividend navable | B31: 1198802 | C31: =B31/$B$15 -> 0.0006117369 | D31: 805386 | E31: =D31/$D$15 -> 0.00039786284 | F31: - | G31: - | H31: - | I31: -
A32: Total Current liabilities | B32: 94953137 | C32: =B32/$B$15 -> 0.048453654 | D32: 204359541 | E32: =D32/$D$15 -> 0.10095416 | F32: 180526344 | G32: =F32/$F$15 -> 0.10974139 | H32: 167448442 | I32: =H32/$H$15 -> 0.10943256
A33: Total equity and liabilities | B33: 1959669259 | C33: =B33/$B$15 -> 1 | D33: 2024280521 | E33: =D33/$D$15 -> 1 | F33: 1645015993 | G33: =F33/$F$15 -> 1 | H33: 1530151943 | I33: =H33/$H$15 -> 1

Sheet Horizontal Analysis(BS) ofDSBSL
A1: Balance Sheet of Dominage Steel Building Systems Limited(Horizontal Analysis)
A4: Particulars | B4: 2022 | C4: Horizontal Analysis | D4: 2021 | E4: Horizontal Analysis | F4: 2020 | G4: Horizontal Analysis | H4: 2019
A5: Property, plant and equipment | B5: 884774242 | C5: =(B5-D5)/D5 -> 0.09879331 | D5: 805223543 | E5: =(D5-F5)/F5 -> 0.07762681 | F5: 747219293 | G5: =(F5-H5)/H5 -> 0.075796508 | H5: 694573079
A6: Right-of-Use (ROU) asset | B6: 1304962 | C6: =(B6-D6)/D6 -> -0.096312362 | D6: 1444041 | E6: - | F6: - | G6: - | H6: -
A7: Projects in Progress (Non-Current Portion) | B7: 192689219 | C7: =(B7-D7)/D7 -> -0.12892916 | D7: 221209585 | E7: =(D7-F7)/F7 -> 0.18689949 | F7: 186376004 | G7: =(F7-H7)/H7 -> 0.044508037 | H7: 178434246
A8: Capital Work in Progress | B8: 18208086 | C8: =(B8-D8)/D8 -> 0.55094033 | D8: 11740030 | E8: =(D8-F8)/F8 -> -0.50977166 | F8: 23948085 | G8: =(F8-H8)/H8 -> 0.34643017 | H8: 17786355
A9: Total Non-current assets | B9: 1096976509 | C9: =(B9-D9)/D9 -> 0.055173491 | D9: 1039617199 | E9: =(D9-F9)/F9 -> 0.085712897 | F9: 957543382 | G9: =(F9-H9)/H9 -> 0.074932842 | H9: 890793680
A10: Inventories | B10: 357081053 | C10: =(B10-D10)/D10 -> -0.06701082 | D10: 382727968 | E10: =(D10-F10)/F10 -> 0.0090435039 | F10: 379297787 | G10: =(F10-H10)/H10 -> 0.13764676 | H10: 333405588
A11: Trade and other receivables | B11: 169136365 | C11: =(B11-D11)/D11 -> -0.035819489 | D11: 175419813 | E11: =(D11-F11)/F11 -> 0.019587155 | F11: 172049846 | G11: =(F11-H11)/H11 -> -0.078481655 | H11: 186702573
A12: Advances, deposits and prepayments | B12: 185473547 | C12: =(B12-D12)/D12 -> 0.38133069 | D12: 134271647 | E12: =(D12-F12)/F12 -> 0.059124583 | F12: 126776065 | G12: =(F12-H12)/H12 -> 0.25586457 | H12: 100947242
A13: Cash and cash equivalents | B13: 151001785 | C13: =(B13-D13)/D13 -> -0.48330217 | D13: 292243893 | E13: =(D13-F13)/F13 -> 30.259665 | F13: 9348913 | G13: =(F13-H13)/H13 -> -0.48921027 | H13: 18302860
A14: Total Current assets | B14: 862692750 | C14: =(B14-D14)/D14 -> -0.12387033 | D14: 984663321 | E14: =(D14-F14)/F14 -> 0.43229462 | F14: 687472611 | G14: =(F14-H14)/H14 -> 0.075254127 | H14: 639358263
A15: Total assets | B15: 1959669259 | C15: =(B15-D15)/D15 -> -0.031918137 | D15: 2024280521 | E15: =(D15-F15)/F15 -> 0.2305537 | F15: 1645015993 | G15: =(F15-H15)/H15 -> 0.075067088 | H15: 1530151943
A16: Stated canital | B16: 1026000000 | C16: =(B16-D16)/D16 -> 0 | D16: 1026000000 | E16: =(D16-F16)/F16 -> 0.57846154 | F16: 650000000 | G16: =(F16-H16)/H16 -> 0 | H16: 650000000
A17: Retained Earninas | B17: 742298212 | C17: =(B17-D17)/D17 -> 0.028005175 | D17: 722076338 | E17: =(D17-F17)/F17 -> -0.010517871 | F17: 729751773 | G17: =(F17-H17)/H17 -> 0.1447493 | H17: 637477371
A18: Equity attributable to owners of the company | B18: 1768298212 | C18: =(B18-D18)/D18 -> 0.011568073 | D18: 1748076338 | E18: =(D18-F18)/F18 -> 0.26694988 | F18: 1379751773 | G18: =(F18-H18)/H18 -> 0.071670698 | H18: 1287477371
... A21: Dofferred Tay I isbilities | B21: 71550905 | C21: =(B21-D21)/D21 -> 0.27327864 | D21: 56194224 | E21: =(D21-F21)/F21 -> -0.28900739 | F21: 79036298 | G21: =(F21-H21)/H21 -> 0.14338509 | H21: 69124828
A22: Lease liability (non-current portion)/ Finance Lease obligations- non-current portion/ Finance Lease Net off current portion | B22: 530250 | C22: =(B22-D22)/D22 -> -0.47463328 | D22: 1009295 | E22: - | F22: - | G22: - | H22: -
A23: Total Non-current liabilities | B23: 96417910 | C23: =(B23-D23)/D23 -> 0.34203339 | D23: 71844643 | E23: =(D23-F23)/F23 -> -0.15215431 | F23: 84737876 | G23: =(F23-H23)/H23 -> 0.12644205 | H23: 75226130
A24: Trade and other pavables | B24: 20754512 | C24: =(B24-D24)/D24 -> 0.060658631 | D24: 19567570 | E24: =(D24-F24)/F24 -> -0.25470703 | F24: 26254870 | G24: =(F24-H24)/H24 -> -0.33480548 | H24: 39469462
A25: Accrued expenses/Provision for expenses/liability for expenses | B25: 2757081 | C25: =(B25-D25)/D25 -> -0.15772039 | D25: 3273356 | E25: =(D25-F25)/F25 -> 0.22208367 | F25: 2678504 | G25: =(F25-H25)/H25 -> -0.058513385 | H25: 2844973
A26: Current portion of term loan | B26: 11452591 | C26: =(B26-D26)/D26 -> 0.45269571 | D26: 7883682 | E26: =(D26-F26)/F26 -> 1.0648597 | F26: 3818023 | G26: =(F26-H26)/H26 -> -0.44694123 | H26: 6903467
A27: Short term loan | B27: 43008343 | C27: =(B27-D27)/D27 -> -0.10269717 | D27: 47930689 | E27: =(D27-F27)/F27 -> 0.081089599 | F27: 44335538 | G27: =(F27-H27)/H27 -> 0.080753054 | H27: 41022820
A28: Income Tay Payable | B28: 11269878 | C28: =(B28-D28)/D28 -> -0.9054085 | D28: 119142610 | E28: =(D28-F28)/F28 -> 0.22865424 | F28: 96970007 | G28: =(F28-H28)/H28 -> 0.38989514 | H28: 69767858
A29: Current portion of lease obligation/ Finance | B29: 482045 | C29: =(B29-D29)/D29 -> 0.083995026 | D29: 444693 | E29: - | F29: - | G29: - | H29: -
A30: Morkorel Drofit Dorticinstion Curd | B30: 4029885 | C30: =(B30-D30)/D30 -> -0.24129845 | D30: 5311555 | E30: =(D30-F30)/F30 -> -0.1789728 | F30: 6469402 | G30: =(F30-H30)/H30 -> -0.13044059 | H30: 7439862
A31: Dividend Payable | B31: 1198802 | C31: =(B31-D31)/D31 -> 0.4884813 | D31: 805386 | E31: - | F31: - | G31: - | H31: -
A32: Total Current liabilities | B32: 94953137 | C32: =(B32-D32)/D32 -> -0.53536235 | D32: 204359541 | E32: =(D32-F32)/F32 -> 0.1320206 | F32: 180526344 | G32: =(F32-H32)/H32 -> 0.078101067 | H32: 167448442
A33: Total equity and liabilities | B33: 1959669259 | C33: =(B33-D33)/D33 -> -0.031918137 | D33: 2024280521 | E33: =(D33-F33)/F33 -> 0.2305537 | F33: 1645015993 | G33: =(F33-H33)/H33 -> 0.075067088 | H33: 1530151943

Sheet IS of DSBSL
A1: Income Statements of Dominage Steel Building Systems Limited
A3: Particulars | C3: 2022 | D3: 2021 | E3: 2020 | F3: 2019
A4: Turnover | C4: 449026637 | D4: 475081252 | E4: 565252592 | F4: 631432785
A5: Cost of cales | C5: 343462589 | D5: 336729098 | E5: 397504187 | F5: 435660715
A6: Gross profit | C6: 105564048 | D6: 138352154 | E6: 167748405 | F6: 195772070
A7: Operating expenses | C7: 25599169 | D7: 28309837 | E7: 25602266 | F7: 27685973
A8: Administrative eynenses | C8: 21239843 | D8: 23480405 | E8: 19993798 | F8: 22336502
A9: Marketing & Selling Expenses | C9: 4359326 | D9: 4829432 | E9: 5608468 | F9: 5349471
A10: Operating profit | C10: 79964878 | D10: 110042316 | E10: 142146139 | F10: 168086097
A11: Other Income/Miccellaneous Income | C11: 10890494 | D11: 8807152 | E11: 273681 | F11: 226139
A12: Non-operating income | C12: 111628 | D12: 3988 | E12: - | F12: -
A13: Finance costs | C13: 6116159 | D13: 7302833 | E13: 6562397 | F13: 12075118
A14: Profit before contribution to workers' profit participation fund | C14: 84627586 | D14: 111542648 | E14: 135857423 | F14: 156237118
A15: Contribution to workers' profit particination fund | C15: 4029885 | D15: 5311555 | E15: 6469401 | F15: 7439863
A16: Profit before taxation | C16: 80597701 | D16: 106231093 | E16: 129388022 | F16: 148797255
A17: Income tax expense | C17: -24566131 | D17: 669471 | E17: 37113619 | F17: 52079040
A18: Current Tax | C18: -9209450 | D18: -22172603 | E18: 27202150 | F18: 33147747
A19: Deferred Tay | C19: -15356681 | D19: 22842074 | E19: 9911469 | F19: 18931293
A20: Profit after tax | C20: 56031570 | D20: 105561622 | E20: 92274403 | F20: 96718215
A21: Earninas Per Share (EPS) | C21: 0.55 | D21: 1.17 | E21: 1.42 | F21: 1.83

Sheet Vertical(IS) of DSBSL
A1: Income Statements of Dominage Steel Building Systems Limited(Vertical Analysis)
A3: Particulars | C3: 2022 | D3: Vertical Analysis (2022) | E3: 2021 | F3: Vertical Analysis (2021) | G3: 2020 | H3: Vertical Analysis (2020) | I3: 2019 | J3: Vertical Analysis (2019)
A4: Turnover | C4: 449026637 | D4: =(C4/$C$4) -> 1 | E4: 475081252 | F4: =E4/$E$4 -> 1 | G4: 565252592 | H4: =G4/$G$4 -> 1 | I4: 631432785 | J4: =I4/$I$4 -> 1
A5: Cost of cales | C5: 343462589 | D5: =(C5/$C$4) -> 0.76490471 | E5: 336729098 | F5: =E5/$E$4 -> 0.70878212 | G5: 397504187 | H5: =G5/$G$4 -> 0.70323284 | I5: 435660715 | J5: =I5/$I$4 -> 0.6899558
A6: Gross profit | C6: 105564048 | D6: =(C6/$C$4) -> 0.23509529 | E6: 138352154 | F6: =E6/$E$4 -> 0.29121788 | G6: 167748405 | H6: =G6/$G$4 -> 0.29676716 | I6: 195772070 | J6: =I6/$I$4 -> 0.3100442
A7: Operating expenses | C7: 25599169 | D7: =(C7/$C$4) -> 0.057010357 | E7: 28309837 | F7: =E7/$E$4 -> 0.059589464 | G7: 25602266 | H7: =G7/$G$4 -> 0.045293496 | I7: 27685973 | J7: =I7/$I$4 -> 0.043846271
A8: Administrative eynenses | C8: 21239843 | D8: =(C8/$C$4) -> 0.047301967 | E8: 23480405 | F8: =E8/$E$4 -> 0.049423977 | G8: 19993798 | H8: =G8/$G$4 -> 0.03537144 | I8: 22336502 | J8: =I8/$I$4 -> 0.035374315
A9: Marketing & Selling Expenses | C9: 4359326 | D9: =(C9/$C$4) -> 0.0097083906 | E9: 4829432 | F9: =E9/$E$4 -> 0.010165486 | G9: 5608468 | H9: =G9/$G$4 -> 0.0099220562 | I9: 5349471 | J9: =I9/$I$4 -> 0.0084719564
A10: Operating profit | C10: 79964878 | D10: =(C10/$C$4) -> 0.17808493 | E10: 110042316 | F10: =E10/$E$4 -> 0.23162841 | G10: 142146139 | H10: =G10/$G$4 -> 0.25147366 | I10: 168086097 | J10: =I10/$I$4 -> 0.26619792
A11: Other Income/Miccellaneous Income | C11: 10890494 | D11: =(C11/$C$4) -> 0.024253559 | E11: 8807152 | F11: =E11/$E$4 -> 0.018538202 | G11: 273681 | H11: =G11/$G$4 -> 0.00048417469 | I11: 226139 | J11: =I11/$I$4 -> 0.0003581363
A12: Non-operating income | C12: 111628 | D12: =(C12/$C$4) -> 0.00024859995 | E12: 3988 | F12: =E12/$E$4 -> 8.3943536e-06 | G12: - | H12: - | I12: - | J12: -
A13: Finance costs | C13: 6116159 | D13: =(C13/$C$4) -> 0.013620927 | E13: 7302833 | F13: =E13/$E$4 -> 0.015371756 | G13: 6562397 | H13: =G13/$G$4 -> 0.011609672 | I13: 12075118 | J13: =I13/$I$4 -> 0.019123362
A14: Profit before contribution to workers' profit participation fund | C14: 84627586 | D14: =(C14/$C$4) -> 0.18846897 | E14: 111542648 | F14: =E14/$E$4 -> 0.23478647 | G14: 135857423 | H14: =G14/$G$4 -> 0.24034816 | I14: 156237118 | J14: =I14/$I$4 -> 0.2474327
A15: Contribution to workers' profit particination fund | C15: 4029885 | D15: =(C15/$C$4) -> 0.0089747126 | E15: 5311555 | F15: =E15/$E$4 -> 0.011180309 | G15: 6469401 | H15: =G15/$G$4 -> 0.011445151 | I15: 7439863 | J15: =I15/$I$4 -> 0.01178251
A16: Profit before taxation | C16: 80597701 | D16: =(C16/$C$4) -> 0.17949425 | E16: 106231093 | F16: =E16/$E$4 -> 0.22360616 | G16: 129388022 | H16: =G16/$G$4 -> 0.22890301 | I16: 148797255 | J16: =I16/$I$4 -> 0.23565019
A17: Income tax expense | C17: -24566131 | D17: =(C17/$C$4) -> -0.054709741 | E17: 669471 | F17: =E17/$E$4 -> 0.0014091716 | G17: 37113619 | H17: =G17/$G$4 -> 0.065658468 | I17: 52079040 | J17: =I17/$I$4 -> 0.082477567
A18: Current Tax | C18: -9209450 | D18: =(C18/$C$4) -> -0.020509808 | E18: -22172603 | F18: =E18/$E$4 -> -0.046671181 | G18: 27202150 | H18: =G18/$G$4 -> 0.048123884 | I18: 33147747 | J18: =I18/$I$4 -> 0.052496082
A19: Deferred Tay | C19: -15356681 | D19: =(C19/$C$4) -> -0.034199933 | E19: 22842074 | F19: =E19/$E$4 -> 0.048080352 | G19: 9911469 | H19: =G19/$G$4 -> 0.017534584 | I19: 18931293 | J19: =I19/$I$4 -> 0.029981486
A20: Profit after tax | C20: 56031570 | D20: =(C20/$C$4) -> 0.12478451 | E20: 105561622 | F20: =E20/$E$4 -> 0.22219699 | G20: 92274403 | H20: =G20/$G$4 -> 0.16324455 | I20: 96718215 | J20: =I20/$I$4 -> 0.15317262

Sheet Horizontal Analysis(IS) ofDSBSL
A1: Income Statements of Dominage Steel Building Systems Limited(Horizontal Analysis)
A3: Particulars | C3: 2022 | D3: Horizontal Analysis(2022) | E3: 2021 | F3: Horizontal Analysis(2021) | G3: 2020 | H3: Horizontal Analysis(2020) | I3: 2019
A4: Turnover | C4: 449026637 | D4: =(C4-E4)/E4 -> -0.05484244 | E4: 475081252 | F4: =(E4-G4)/G4 -> -0.15952397 | G4: 565252592 | H4: =(G4-I4)/I4 -> -0.10480956 | I4: 631432785
A5: Cost of cales | C5: 343462589 | D5: =(C5-E5)/E5 -> 0.01999676 | E5: 336729098 | F5: =(E5-G5)/G5 -> -0.1528917 | G5: 397504187 | H5: =(G5-I5)/I5 -> -0.087583128 | I5: 435660715
A6: Gross profit | C6: 105564048 | D6: =(C6-E6)/E6 -> -0.23699021 | E6: 138352154 | F6: =(E6-G6)/G6 -> -0.17524012 | G6: 167748405 | H6: =(G6-I6)/I6 -> -0.14314435 | I6: 195772070
A7: Operating expenses | C7: 25599169 | D7: =(C7-E7)/E7 -> -0.095750039 | E7: 28309837 | F7: =(E7-G7)/G7 -> 0.10575513 | G7: 25602266 | H7: =(G7-I7)/I7 -> -0.075262191 | I7: 27685973
A8: Administrative eynenses | C8: 21239843 | D8: =(C8-E8)/E8 -> -0.09542263 | E8: 23480405 | F8: =(E8-G8)/G8 -> 0.17438443 | G8: 19993798 | H8: =(G8-I8)/I8 -> -0.10488231 | I8: 22336502
A9: Marketing & Selling Expenses | C9: 4359326 | D9: =(C9-E9)/E9 -> -0.097341882 | E9: 4829432 | F9: =(E9-G9)/G9 -> -0.13890353 | G9: 5608468 | H9: =(G9-I9)/I9 -> 0.048415441 | I9: 5349471
A10: Operating profit | C10: 79964878 | D10: =(C10-E10)/E10 -> -0.27332611 | E10: 110042316 | F10: =(E10-G10)/G10 -> -0.22585083 | G10: 142146139 | H10: =(G10-I10)/I10 -> -0.15432542 | I10: 168086097
A11: Other Income/Miccellaneous Income | C11: 10890494 | D11: =(C11-E11)/E11 -> 0.23655116 | E11: 8807152 | F11: =(E11-G11)/G11 -> 31.180356 | G11: 273681 | H11: =(G11-I11)/I11 -> 0.21023353 | I11: 226139
A12: Non-operating income | C12: 111628 | D12: =(C12-E12)/E12 -> 26.990973 | E12: 3988 | G12: - | I12: -
A13: Finance costs | C13: 6116159 | D13: =(C13-E13)/E13 -> -0.16249502 | E13: 7302833 | F13: =(E13-G13)/G13 -> 0.11283011 | G13: 6562397 | H13: =(G13-I13)/I13 -> -0.45653558 | I13: 12075118
A14: Profit before contribution to workers' profit participation fund | C14: 84627586 | D14: =(C14-E14)/E14 -> -0.2412984 | E14: 111542648 | F14: =(E14-G14)/G14 -> -0.17897274 | G14: 135857423 | H14: =(G14-I14)/I14 -> -0.1304408 | I14: 156237118
A15: Contribution to workers' profit particination fund | C15: 4029885 | D15: =(C15-E15)/E15 -> -0.24129845 | E15: 5311555 | F15: =(E15-G15)/G15 -> -0.17897267 | G15: 6469401 | H15: =(G15-I15)/I15 -> -0.13044084 | I15: 7439863
A16: Profit before taxation | C16: 80597701 | D16: =(C16-E16)/E16 -> -0.24129839 | E16: 106231093 | F16: =(E16-G16)/G16 -> -0.17897274 | G16: 129388022 | H16: =(G16-I16)/I16 -> -0.1304408 | I16: 148797255
A17: Income tax expense | C17: -24566131 | D17: =(C17-E17)/E17 -> -37.69484 | E17: 669471 | F17: =(E17-G17)/G17 -> -0.98196158 | G17: 37113619 | H17: =(G17-I17)/I17 -> -0.28735977 | I17: 52079040
A18: Current Tax | C18: -9209450 | D18: =(C18-E18)/E18 -> -0.58464732 | E18: -22172603 | F18: =(E18-G18)/G18 -> -1.8151048 | G18: 27202150 | H18: =(G18-I18)/I18 -> -0.17936655 | I18: 33147747
A19: Deferred Tay | C19: -15356681 | D19: =(C19-E19)/E19 -> -1.672298 | E19: 22842074 | F19: =(E19-G19)/G19 -> 1.3046103 | G19: 9911469 | H19: =(G19-I19)/I19 -> -0.4764505 | I19: 18931293
A20: Profit after tax | C20: 56031570 | D20: =(C20-E20)/E20 -> -0.46920511 | E20: 105561622 | F20: =(E20-G20)/G20 -> 0.1439968 | G20: 92274403 | H20: =(G20-I20)/I20 -> -0.045945968 | I20: 96718215
A21: Earninas Per Share (EPS) | C21: 0.55 | D21: =(C21-E21)/E21 -> -0.52991453 | E21: 1.17 | F21: =(E21-G21)/G21 -> -0.17605634 | G21: 1.42 | H21: =(G21-I21)/I21 -> -0.22404372 | I21: 1.83

Sheet Ratio Analysis
G2: Ratio Analysis of Dominage Steel Building Systems Limited
G4: Ratio Name | I4: 2022 | J4: 2021 | K4: 2020 | L4: 2019
G6: Liquidity Ratio:
G8: Current Ratio | I8: ='BS of DSBSL'!C14/'BS of DSBSL'!C32 -> 9.0854581 | J8: ='BS of DSBSL'!D14/'BS of DSBSL'!D32 -> 4.818289 | K8: ='BS of DSBSL'!E14/'BS of DSBSL'!E32 -> 3.8081567 | L8: ='BS of DSBSL'!F14/'BS of DSBSL'!F32 -> 3.8182395
G9: Quick Ratio | I9: =('BS of DSBSL'!C13+'BS of DSBSL'!C11)/'BS of DSBSL'!C32 -> 3.3715384 | J9: =('BS of DSBSL'!D13+'BS of DSBSL'!D11)/'BS of DSBSL'!D32 -> 2.2884359 | K9: =('BS of DSBSL'!E13+'BS of DSBSL'!E11)/'BS of DSBSL'!E32 -> 1.0048326 | L9: =('BS of DSBSL'!F13+'BS of DSBSL'!F11)/'BS of DSBSL'!F32 -> 1.2242899
G10: Account Receivable Turnover | I10: ='IS of DSBSL'!C4/(('BS of DSBSL'!C11+'BS of DSBSL'!D11)/2) -> 2.606406 | J10: ='IS of DSBSL'!D4/(('BS of DSBSL'!D11+'BS of DSBSL'!E11)/2) -> 2.7345193 | K10: ='IS of DSBSL'!E4/(('BS of DSBSL'!E11+'BS of DSBSL'!F11)/2) -> 3.1512127 | L10: ='IS of DSBSL'!F4/(('BS of DSBSL'!F11+'BS of DSBSL'!G11)/2) -> 6.7640502
G11: Average Collection Period | I11: =365/I10 -> 140.03958 | J11: =365/J10 -> 133.47867 | K11: =365/K10 -> 115.82842 | L11: =365/L10 -> 53.961752
G12: Inventory Turnover | I12: ='IS of DSBSL'!C5/(('BS of DSBSL'!C10+'BS of DSBSL'!D10)/2) -> 0.9285169 | J12: ='IS of DSBSL'!D5/(('BS of DSBSL'!D10+'BS of DSBSL'!E10)/2) -> 0.88377354 | K12: ='IS of DSBSL'!E5/(('BS of DSBSL'!E10+'BS of DSBSL'!F10)/2) -> 1.1154828 | L12: ='IS of DSBSL'!F5/(('BS of DSBSL'!F10+'BS of DSBSL'!G10)/2) -> 2.6133978
G13: Days in Inventory | I13: =365/I12 -> 393.10001 | J13: =365/J12 -> 413.00173 | K13: =365/K12 -> 327.21257 | L13: =365/L12 -> 139.66492
G15: Profitability Ratio:
G17: Profit margin | I17: ='IS of DSBSL'!C20/'IS of DSBSL'!C4 -> 0.12478451 | J17: ='IS of DSBSL'!D20/'IS of DSBSL'!D4 -> 0.22219699 | K17: ='IS of DSBSL'!E20/'IS of DSBSL'!E4 -> 0.16324455 | L17: ='IS of DSBSL'!F20/'IS of DSBSL'!F4 -> 0.15317262
G18: Asset Turnover | I18: ='IS of DSBSL'!C4/(('BS of DSBSL'!C15+'BS of DSBSL'!D15)/2) -> 0.22541782 | J18: ='IS of DSBSL'!D4/(('BS of DSBSL'!D15+'BS of DSBSL'!E15)/2) -> 0.2589495 | K18: ='IS of DSBSL'!E4/(('BS of DSBSL'!E15+'BS of DSBSL'!F15)/2) -> 0.35604579 | L18: ='IS of DSBSL'!F4/(('BS of DSBSL'!F15+'BS of DSBSL'!G15)/2) -> 0.82532037
G19: Return on Assets | I19: ='IS of DSBSL'!C20/(('BS of DSBSL'!C15+'BS of DSBSL'!D15)/2) -> 0.028128653 | J19: ='IS of DSBSL'!D20/(('BS of DSBSL'!D15+'BS of DSBSL'!E15)/2) -> 0.057537799 | K19: ='IS of DSBSL'!E20/(('BS of DSBSL'!E15+'BS of DSBSL'!F15)/2) -> 0.058122534 | L19: ='IS of DSBSL'!F20/(('BS of DSBSL'!F15+'BS of DSBSL'!G15)/2) -> 0.12641648
G20: Earning Per Share(EPS) | I20: 0.55 | J20: 1.17 | K20: 1.42 | L20: 1.83
G21: Price Earning Ratio | I21: ='BS of DSBSL'!C34/'Ratio Analysis'!I20 -> 38.218182 | J21: ='BS of DSBSL'!D34/'Ratio Analysis'!J20 -> 20.957265 | K21: ='BS of DSBSL'!E34/'Ratio Analysis'!K20 -> 24.260563
G23: Solvency Ratio:
G25: Debt to Asset Ratio | I25: =('BS of DSBSL'!C32+'BS of DSBSL'!C23)/'BS of DSBSL'!C15 -> 0.097654768 | J25: =('BS of DSBSL'!D32+'BS of DSBSL'!D23)/'BS of DSBSL'!D15 -> 0.13644561 | K25: =('BS of DSBSL'!E32+'BS of DSBSL'!E23)/'BS of DSBSL'!E15 -> 0.16125328 | L25: 0.15
